{"dependencies":[{"name":"/Users/keshiamukenge/Documents/projets/threejs-2/package.json","includedInParent":true,"mtime":1638746028084},{"name":"./js/Webgl.js","loc":{"line":1,"column":18},"parent":"/Users/keshiamukenge/Documents/projets/threejs-2/src/App.js","resolved":"/Users/keshiamukenge/Documents/projets/threejs-2/src/js/Webgl.js"},{"name":"./js/Animations","loc":{"line":2,"column":23},"parent":"/Users/keshiamukenge/Documents/projets/threejs-2/src/App.js","resolved":"/Users/keshiamukenge/Documents/projets/threejs-2/src/js/Animations.js"},{"name":"./js/Gui.js","loc":{"line":3,"column":16},"parent":"/Users/keshiamukenge/Documents/projets/threejs-2/src/App.js","resolved":"/Users/keshiamukenge/Documents/projets/threejs-2/src/js/Gui.js"}],"generated":{"js":"'use strict';\n\nvar _Webgl = require('./js/Webgl.js');\n\nvar _Webgl2 = _interopRequireDefault(_Webgl);\n\nvar _Animations = require('./js/Animations');\n\nvar _Animations2 = _interopRequireDefault(_Animations);\n\nvar _Gui = require('./js/Gui.js');\n\nvar _Gui2 = _interopRequireDefault(_Gui);\n\nfunction _interopRequireDefault(obj) { return obj && obj.__esModule ? obj : { default: obj }; }\n\nclass App {\n    constructor() {\n        this.animations = new _Animations2.default();\n        this.webgl = new _Webgl2.default();\n        this.controller = new _Gui2.default();\n    }\n}\n\nnew App();","map":{"mappings":[{"generated":{"line":3,"column":0},"source":"App.js","original":{"line":1,"column":0}},{"generated":{"line":7,"column":0},"source":"App.js","original":{"line":2,"column":0}},{"generated":{"line":11,"column":0},"source":"App.js","original":{"line":3,"column":0}},{"generated":{"line":17,"column":0},"source":"App.js","original":{"line":5,"column":0}},{"name":"App","generated":{"line":17,"column":6},"source":"App.js","original":{"line":5,"column":6}},{"generated":{"line":17,"column":9},"source":"App.js","original":{"line":5,"column":0}},{"generated":{"line":17,"column":10},"source":"App.js","original":{"line":5,"column":10}},{"name":"constructor","generated":{"line":18,"column":0},"source":"App.js","original":{"line":6,"column":4}},{"generated":{"line":18,"column":18},"source":"App.js","original":{"line":6,"column":18}},{"generated":{"line":19,"column":0},"source":"App.js","original":{"line":7,"column":8}},{"name":"animations","generated":{"line":19,"column":13},"source":"App.js","original":{"line":7,"column":13}},{"generated":{"line":19,"column":23},"source":"App.js","original":{"line":7,"column":8}},{"generated":{"line":19,"column":26},"source":"App.js","original":{"line":7,"column":26}},{"name":"Animations","generated":{"line":19,"column":30},"source":"App.js","original":{"line":7,"column":30}},{"generated":{"line":19,"column":50},"source":"App.js","original":{"line":7,"column":26}},{"generated":{"line":19,"column":52},"source":"App.js","original":{"line":7,"column":8}},{"generated":{"line":20,"column":0},"source":"App.js","original":{"line":8,"column":8}},{"name":"webgl","generated":{"line":20,"column":13},"source":"App.js","original":{"line":8,"column":13}},{"generated":{"line":20,"column":18},"source":"App.js","original":{"line":8,"column":8}},{"generated":{"line":20,"column":21},"source":"App.js","original":{"line":8,"column":21}},{"name":"Webgl","generated":{"line":20,"column":25},"source":"App.js","original":{"line":8,"column":25}},{"generated":{"line":20,"column":40},"source":"App.js","original":{"line":8,"column":21}},{"generated":{"line":20,"column":42},"source":"App.js","original":{"line":8,"column":8}},{"generated":{"line":21,"column":0},"source":"App.js","original":{"line":9,"column":8}},{"name":"controller","generated":{"line":21,"column":13},"source":"App.js","original":{"line":9,"column":13}},{"generated":{"line":21,"column":23},"source":"App.js","original":{"line":9,"column":8}},{"generated":{"line":21,"column":26},"source":"App.js","original":{"line":9,"column":26}},{"name":"Gui","generated":{"line":21,"column":30},"source":"App.js","original":{"line":9,"column":30}},{"generated":{"line":21,"column":43},"source":"App.js","original":{"line":9,"column":26}},{"generated":{"line":21,"column":45},"source":"App.js","original":{"line":9,"column":8}},{"generated":{"line":22,"column":0},"source":"App.js","original":{"line":10,"column":5}},{"generated":{"line":23,"column":0},"source":"App.js","original":{"line":5,"column":10}},{"generated":{"line":25,"column":0},"source":"App.js","original":{"line":13,"column":0}},{"name":"App","generated":{"line":25,"column":4},"source":"App.js","original":{"line":13,"column":4}},{"generated":{"line":25,"column":7},"source":"App.js","original":{"line":13,"column":0}}],"sources":{"App.js":"import Webgl from './js/Webgl.js';\nimport Animations from \"./js/Animations\";\nimport Gui from './js/Gui.js';\n\nclass App {\n    constructor() {\n        this.animations = new Animations();\n        this.webgl = new Webgl();\n        this.controller = new Gui();\n    }\n}\n\nnew App();"},"lineCount":null}},"hash":"cfdcc29d82f03c2e066a77e3ca1b74cb","cacheData":{"env":{}},"id":9}